dopes/__init__.py
dopes/data_analysis/__init__.py
dopes/data_analysis/data_processing.py
dopes/data_analysis/diode.py
dopes/data_analysis/file_handling.py
dopes/data_analysis/mechanics.py
dopes/data_analysis/polytec.py
dopes/data_analysis/raman.py
dopes/data_analysis/semiconductor.py
dopes/data_analysis/transistor.py
dopes/equipment_control/__init__.py
dopes/equipment_control/cm110.py
dopes/equipment_control/dmm.py
dopes/equipment_control/equipment.py
dopes/equipment_control/hp4145.py
dopes/equipment_control/k2400.py
dopes/equipment_control/k2450.py
dopes/equipment_control/k4200.py
dopes/equipment_control/kal100.py
dopes/equipment_control/meerstetterTEC.py
dopes/equipment_control/oscilloscope.py
dopes/equipment_control/pm100d.py
dopes/equipment_control/sh242.py
dopes/equipment_control/signal_generator.py
dopes/equipment_control/mecom/__init__.py
dopes/equipment_control/mecom/commands.py
dopes/equipment_control/mecom/exceptions.py
dopes/equipment_control/mecom/mecom.py
dopes-2025.1.0.dist-info/METADATA
dopes-2025.1.0.dist-info/WHEEL
dopes-2025.1.0.dist-info/licenses/LICENSE-CC-BY-NC-SA
dopes-2025.1.0.dist-info/RECORD
