Metadata-Version: 2.4
Name: dopes
Version: 2025.1.0
Summary: Data analysis and operation software
Project-URL: Repository, https://forge.uclouvain.be/welcome/dopes
Author-email: Nicolas Roisin <nicolas.roisin@uclouvain.be>, Loïc Lahaye <loic.lahaye@uclouvain.be>
License-Expression: CC-BY-NC-SA-4.0
License-File: LICENSE-CC-BY-NC-SA
Requires-Python: >=3.0
Requires-Dist: numpy
Requires-Dist: pyserial
Requires-Dist: pyvisa
Requires-Dist: scipy
